<annotation>
	<folder>‭lion</folder>
	<filename>OIP.b9170-1ZJet0fSO9r_b9VgAAAA.jpg</filename>
	<path>C:\Users\marhr\Desktop\‭lion\OIP.b9170-1ZJet0fSO9r_b9VgAAAA.jpg</path>
	<source>
		<database>Unknown</database>
	</source>
	<size>
		<width>157</width>
		<height>236</height>
		<depth>3</depth>
	</size>
	<segmented>0</segmented>
	<object>
		<name>lion</name>
		<pose>Unspecified</pose>
		<truncated>0</truncated>
		<difficult>0</difficult>
		<bndbox>
			<xmin>80</xmin>
			<ymin>185</ymin>
			<xmax>112</xmax>
			<ymax>214</ymax>
		</bndbox>
	</object>
</annotation>
